yorg_test/__init__.py
yorg_test/core/__init__.py
yorg_test/core/agents/__init__.py
yorg_test/core/agents/base_agent.py
yorg_test/core/agents/data_scientist/data_scientist.py
yorg_test/core/agents/data_scientist/data_scientist_prompt.py
yorg_test/core/agents/software_engineer/repo_manager.py
yorg_test/core/agents/software_engineer/software_engineer.py
yorg_test/core/agents/software_engineer/software_engineer_prompt.py
yorg_test/core/assistant/__init__.py
yorg_test/core/assistant/assistant.py
yorg_test/core/assistant/async_threads.py
yorg_test/core/assistant/config.py
yorg_test/core/assistant/prompt/few_shot_cot_tools_choose_prompt.py
yorg_test/core/assistant/prompt/few_shot_extract_parametes_from_input.py
yorg_test/core/assistant/prompt/few_shot_response_prompt.py
yorg_test/core/assistant/prompt/few_shot_tools_choose_prompt.py
yorg_test/core/assistant/prompt/parameters_generate_prompt.py
yorg_test/core/assistant/prompt/response_generate_prompt.py
yorg_test/core/assistant/threads.py
yorg_test/core/assistant/tools/example_stateful_tool.yaml
yorg_test/core/assistant/tools/example_stateful_tool_entity.py
yorg_test/core/assistant/tools/model.py
yorg_test/core/assistant/tools/stateful_tool_entity.py
yorg_test/core/assistant/tools/swe_tool.yaml
yorg_test/core/assistant/tools/swe_tool_entity.py
yorg_test/core/assistant/tools/tool_entity.py
yorg_test/core/assistant/tools/tools.py
yorg_test/core/assistant/tools/tools.yaml
yorg_test/core/common_models.py
yorg_test/core/nodes/__init__.py
yorg_test/core/nodes/base_node.py
yorg_test/core/nodes/code_runner/code_runner.py
yorg_test/core/nodes/code_runner/code_runner_model.py
yorg_test/core/nodes/data_analysis/data_analysis.py
yorg_test/core/nodes/data_analysis/data_analysis_model.py
yorg_test/core/nodes/document_loader/document_loader.py
yorg_test/core/nodes/document_loader/document_model.py
yorg_test/core/nodes/git/file_io.py
yorg_test/core/nodes/git/file_io_model.py
yorg_test/core/nodes/git/git_base_node.py
phireact-0.0.1.dist-info/LICENSE
phireact-0.0.1.dist-info/WHEEL
phireact-0.0.1.dist-info/METADATA
phireact-0.0.1.dist-info/RECORD
