Metadata-Version: 2.1
Name: phireact
Version: 0.0.1
Summary: test package for yorg
Author: zxy
Author-email: zhongxingyuemail@gmail.com
Requires-Python: >=3.8
Classifier: Programming Language :: Python :: 3
Classifier: Programming Language :: Python :: 3.10
Classifier: Programming Language :: Python :: 3.8
Classifier: Programming Language :: Python :: 3.9
Requires-Dist: include
